{
  "stats": {
    "commits": 0,
    "pullRequests": 2,
    "issues": 1,
    "reviews": 4
  },
  "contributions": [
    {
      "title": "Pushed commits to Pritz395/MY-GSOC-TOOL",
      "description": "Code changes",
      "date": "2026-01-15",
      "url": "https://github.com/Pritz395/MY-GSOC-TOOL",
      "type": "commit"
    },
    {
      "title": "Pushed commits to Pritz395/MY-GSOC-TOOL",
      "description": "Code changes",
      "date": "2026-01-15",
      "url": "https://github.com/Pritz395/MY-GSOC-TOOL",
      "type": "commit"
    },
    {
      "title": "Pushed commits to Pritz395/MY-GSOC-TOOL",
      "description": "Code changes",
      "date": "2026-01-14",
      "url": "https://github.com/Pritz395/MY-GSOC-TOOL",
      "type": "commit"
    },
    {
      "title": "Pushed commits to Pritz395/BLT",
      "description": "Code changes",
      "date": "2026-01-14",
      "url": "https://github.com/Pritz395/BLT",
      "type": "commit"
    },
    {
      "title": "Pushed commits to Pritz395/BLT",
      "description": "Code changes",
      "date": "2026-01-12",
      "url": "https://github.com/Pritz395/BLT",
      "type": "commit"
    },
    {
      "title": "Pushed commits to Pritz395/BLT",
      "description": "Code changes",
      "date": "2026-01-12",
      "url": "https://github.com/Pritz395/BLT",
      "type": "commit"
    },
    {
      "title": "Pushed commits to Pritz395/BLT",
      "description": "Code changes",
      "date": "2026-01-12",
      "url": "https://github.com/Pritz395/BLT",
      "type": "commit"
    },
    {
      "title": "Pushed commits to Pritz395/BLT",
      "description": "Code changes",
      "date": "2026-01-12",
      "url": "https://github.com/Pritz395/BLT",
      "type": "commit"
    },
    {
      "title": "Pushed commits to Pritz395/BLT",
      "description": "Code changes",
      "date": "2026-01-12",
      "url": "https://github.com/Pritz395/BLT",
      "type": "commit"
    },
    {
      "title": "Pushed commits to Pritz395/BLT",
      "description": "Code changes",
      "date": "2026-01-12",
      "url": "https://github.com/Pritz395/BLT",
      "type": "commit"
    },
    {
      "title": "Pushed commits to Pritz395/BLT",
      "description": "Code changes",
      "date": "2026-01-12",
      "url": "https://github.com/Pritz395/BLT",
      "type": "commit"
    },
    {
      "title": "Pushed commits to Pritz395/BLT",
      "description": "Code changes",
      "date": "2026-01-12",
      "url": "https://github.com/Pritz395/BLT",
      "type": "commit"
    },
    {
      "title": "Pushed commits to Pritz395/BLT",
      "description": "Code changes",
      "date": "2026-01-12",
      "url": "https://github.com/Pritz395/BLT",
      "type": "commit"
    },
    {
      "title": "Pushed commits to Pritz395/BLT",
      "description": "Code changes",
      "date": "2026-01-12",
      "url": "https://github.com/Pritz395/BLT",
      "type": "commit"
    },
    {
      "title": "Pushed commits to Pritz395/BLT",
      "description": "Code changes",
      "date": "2026-01-12",
      "url": "https://github.com/Pritz395/BLT",
      "type": "commit"
    },
    {
      "title": "Pushed commits to Pritz395/BLT",
      "description": "Code changes",
      "date": "2026-01-12",
      "url": "https://github.com/Pritz395/BLT",
      "type": "commit"
    },
    {
      "title": "Pushed commits to Pritz395/BLT",
      "description": "Code changes",
      "date": "2026-01-12",
      "url": "https://github.com/Pritz395/BLT",
      "type": "commit"
    },
    {
      "title": "Pushed commits to Pritz395/BLT",
      "description": "Code changes",
      "date": "2026-01-12",
      "url": "https://github.com/Pritz395/BLT",
      "type": "commit"
    },
    {
      "title": "Pushed commits to Pritz395/BLT",
      "description": "Code changes",
      "date": "2026-01-12",
      "url": "https://github.com/Pritz395/BLT",
      "type": "commit"
    },
    {
      "title": "Pushed commits to Pritz395/BLT",
      "description": "Code changes",
      "date": "2026-01-12",
      "url": "https://github.com/Pritz395/BLT",
      "type": "commit"
    }
  ],
  "lastUpdated": "2026-01-15T10:41:31.238Z"
}